[
 {
   "Recipe #": 1,
   "Name": "Mushroom Skewer",
   "Inventory Icon": "https://raw.githubusercontent.com/TOTKSheet/TOTKImages/main/Items/Item_Cook_A_01.png",
   "Caption": "This simple mushroom-packed skewer has its\ncolorful presentation to thank for its appeal.",
   "Required Ingredient 1": "Mushroom",
   "Required Ingredient 2": "-",
   "Required Ingredient 3": "-",
   "Required Ingredient 4": "-",
   "Required Ingredient 5": "-",
   "Cooking Method": "Cooking Pot"
 },
 {
   "Recipe #": 2,
   "Name": "Meat and Mushroom Skewer",
   "Inventory Icon": "https://raw.githubusercontent.com/TOTKSheet/TOTKImages/main/Items/Item_Cook_A_09.png",
   "Caption": "A filling dish made by grilling various\nmountain ingredients with meat.",
   "Required Ingredient 1": "Mushroom",
   "Required Ingredient 2": "Meat",
   "Required Ingredient 3": "-",
   "Required Ingredient 4": "-",
   "Required Ingredient 5": "-",
   "Cooking Method": "Cooking Pot"
 },
 {
   "Recipe #": 3,
   "Name": "Fish and Mushroom Skewer",
   "Inventory Icon": "https://raw.githubusercontent.com/TOTKSheet/TOTKImages/main/Items/Item_Cook_A_08.png",
   "Caption": "A simple dish made by cooking skewered\nfresh fish alongside fragrant mushrooms.",
   "Required Ingredient 1": "Mushroom",
   "Required Ingredient 2": "Fish",
   "Required Ingredient 3": "-",
   "Required Ingredient 4": "-",
   "Required Ingredient 5": "-",
   "Cooking Method": "Cooking Pot"
 },
 {
   "Recipe #": 4,
   "Name": "Meat Skewer",
   "Inventory Icon": "https://raw.githubusercontent.com/TOTKSheet/TOTKImages/main/Items/Item_Cook_B_06.png",
   "Caption": "A juicy, filling snack made by grilling small\nchunks of meat on a skewer.",
   "Required Ingredient 1": "Meat",
   "Required Ingredient 2": "-",
   "Required Ingredient 3": "-",
   "Required Ingredient 4": "-",
   "Required Ingredient 5": "-",
   "Cooking Method": "Cooking Pot"
 },
 {
   "Recipe #": 5,
   "Name": "Fish Skewer",
   "Inventory Icon": "https://raw.githubusercontent.com/TOTKSheet/TOTKImages/main/Items/Item_Cook_B_05.png",
   "Caption": "A simple dish made by cooking chunks of\nfresh fish on a skewer.",
   "Required Ingredient 1": "Fish",
   "Required Ingredient 2": "-",
   "Required Ingredient 3": "-",
   "Required Ingredient 4": "-",
   "Required Ingredient 5": "-",
   "Cooking Method": "Cooking Pot"
 },
 {
   "Recipe #": 6,
   "Name": "Seafood Skewer",
   "Inventory Icon": "https://raw.githubusercontent.com/TOTKSheet/TOTKImages/main/Items/Item_Cook_B_23.png",
   "Caption": "A skewer of delicious roasted fish\nand shellfish.",
   "Required Ingredient 1": "Seafood",
   "Required Ingredient 2": "-",
   "Required Ingredient 3": "-",
   "Required Ingredient 4": "-",
   "Required Ingredient 5": "-",
   "Cooking Method": "Cooking Pot"
 },
 {
   "Recipe #": 7,
   "Name": "Copious Meat Skewers",
   "Inventory Icon": "https://raw.githubusercontent.com/TOTKSheet/TOTKImages/main/Items/Item_Cook_B_16.png",
   "Caption": "Just shove a bunch of meat onto a skewer,\nand you're good to go.",
   "Required Ingredient 1": "Meat",
   "Required Ingredient 2": "Meat",
   "Required Ingredient 3": "Meat",
   "Required Ingredient 4": "Meat",
   "Required Ingredient 5": "-",
   "Cooking Method": "Cooking Pot"
 },
 {
   "Recipe #": 8,
   "Name": "Copious Seafood Skewers",
   "Inventory Icon": "https://raw.githubusercontent.com/TOTKSheet/TOTKImages/main/Items/Item_Cook_B_15.png",
   "Caption": "It's just a whole heap of stuff shoved onto a\nskewer, but it's still a pretty tasty dish.",
   "Required Ingredient 1": "Fish",
   "Required Ingredient 2": "Fish",
   "Required Ingredient 3": "Fish",
   "Required Ingredient 4": "Fish",
   "Required Ingredient 5": "-",
   "Cooking Method": "Cooking Pot"
 },
 {
   "Recipe #": 9,
   "Name": "Steamed Fruit",
   "Inventory Icon": "https://raw.githubusercontent.com/TOTKSheet/TOTKImages/main/Items/Item_Cook_A_03.png",
   "Caption": "A regional dish made by steaming near-\nripened fruits in the leaves of fragrant plants.",
   "Required Ingredient 1": "Plant",
   "Required Ingredient 2": "Fruit",
   "Required Ingredient 3": "-",
   "Required Ingredient 4": "-",
   "Required Ingredient 5": "-",
   "Cooking Method": "Cooking Pot"
 },
 {
   "Recipe #": 10,
   "Name": "Steamed Tomatoes",
   "Inventory Icon": "https://raw.githubusercontent.com/TOTKSheet/TOTKImages/main/Items/Item_Cook_Q_03.png",
   "Caption": "Tomato cooked while wrapped in a leaf. The\nheat brings out its medicinal effect.",
   "Required Ingredient 1": "Plant",
   "Required Ingredient 2": "Hylian Tomato",
   "Required Ingredient 3": "-",
   "Required Ingredient 4": "-",
   "Required Ingredient 5": "-",
   "Cooking Method": "Cooking Pot"
 },
 {
   "Recipe #": 11,
   "Name": "Steamed Mushrooms",
   "Inventory Icon": "https://raw.githubusercontent.com/TOTKSheet/TOTKImages/main/Items/Item_Cook_A_02.png",
   "Caption": "A healthy vegetable dish achieved by\nsteaming mushrooms in plant leaves.",
   "Required Ingredient 1": "Plant",
   "Required Ingredient 2": "Mushroom",
   "Required Ingredient 3": "-",
   "Required Ingredient 4": "-",
   "Required Ingredient 5": "-",
   "Cooking Method": "Cooking Pot"
 },
 {
   "Recipe #": 12,
   "Name": "Steamed Meat",
   "Inventory Icon": "https://raw.githubusercontent.com/TOTKSheet/TOTKImages/main/Items/Item_Cook_A_05.png",
   "Caption": "This meat dish has been wrapped in fragrant\nleaves and steamed to preserve its moisture.",
   "Required Ingredient 1": "Plant",
   "Required Ingredient 2": "Meat",
   "Required Ingredient 3": "-",
   "Required Ingredient 4": "-",
   "Required Ingredient 5": "-",
   "Cooking Method": "Cooking Pot"
 },
 {
   "Recipe #": 13,
   "Name": "Steamed Fish",
   "Inventory Icon": "https://raw.githubusercontent.com/TOTKSheet/TOTKImages/main/Items/Item_Cook_A_04.png",
   "Caption": "A refined dish made by wrapping a fresh fish\nin fragrant wild greens and cooking it.",
   "Required Ingredient 1": "Plant",
   "Required Ingredient 2": "Fish",
   "Required Ingredient 3": "-",
   "Required Ingredient 4": "-",
   "Required Ingredient 5": "-",
   "Cooking Method": "Cooking Pot"
 },
 {
   "Recipe #": 14,
   "Name": "Sautéed Peppers",
   "Inventory Icon": "https://raw.githubusercontent.com/TOTKSheet/TOTKImages/main/Items/Item_Cook_B_21.png",
   "Caption": "The spiciness of these sautéed peppers has\nbeen broken by the heat for a sweeter taste.",
   "Required Ingredient 1": "Spicy Pepper",
   "Required Ingredient 2": "-",
   "Required Ingredient 3": "-",
   "Required Ingredient 4": "-",
   "Required Ingredient 5": "-",
   "Cooking Method": "Cooking Pot"
 },
 {
   "Recipe #": 15,
   "Name": "Sautéed Nuts",
   "Inventory Icon": "https://raw.githubusercontent.com/TOTKSheet/TOTKImages/main/Items/Item_Cook_B_22.png",
   "Caption": "These sautéed tree seeds are the perfect\nsnack for the busy adventurer on the go!",
   "Required Ingredient 1": "Nut",
   "Required Ingredient 2": "-",
   "Required Ingredient 3": "-",
   "Required Ingredient 4": "-",
   "Required Ingredient 5": "-",
   "Cooking Method": "Cooking Pot"
 },
 {
   "Recipe #": 16,
   "Name": "Fried Wild Greens",
   "Inventory Icon": "https://raw.githubusercontent.com/TOTKSheet/TOTKImages/main/Items/Item_Cook_B_01.png",
   "Caption": "A basic vegetable dish made by sautéing\nfresh wild plants.",
   "Required Ingredient 1": "Plant",
   "Required Ingredient 2": "-",
   "Required Ingredient 3": "-",
   "Required Ingredient 4": "-",
   "Required Ingredient 5": "-",
   "Cooking Method": "Cooking Pot"
 },
 {
   "Recipe #": 17,
   "Name": "Copious Fried Wild Greens",
   "Inventory Icon": "https://raw.githubusercontent.com/TOTKSheet/TOTKImages/main/Items/Item_Cook_B_11.png",
   "Caption": "A healthy dish made by cooking mixed \ngreens over a strong flame.",
   "Required Ingredient 1": "Plant",
   "Required Ingredient 2": "Plant",
   "Required Ingredient 3": "Plant",
   "Required Ingredient 4": "Plant",
   "Required Ingredient 5": "-",
   "Cooking Method": "Cooking Pot"
 },
 {
   "Recipe #": 18,
   "Name": "Cooked Stambulb",
   "Inventory Icon": "https://raw.githubusercontent.com/TOTKSheet/TOTKImages/main/Items/Item_Cook_Q_06.png",
   "Caption": "A wild dish of a whole stambulb roasted\nwith its skin on. Sweet and tasty.",
   "Required Ingredient 1": "Stambulb",
   "Required Ingredient 2": "-",
   "Required Ingredient 3": "-",
   "Required Ingredient 4": "-",
   "Required Ingredient 5": "-",
   "Cooking Method": "Cooking Pot"
 },
 {
   "Recipe #": 19,
   "Name": "Buttered Stambulb",
   "Inventory Icon": "https://raw.githubusercontent.com/TOTKSheet/TOTKImages/main/Items/Item_Cook_Q_07.png",
   "Caption": "A simple dish of stambulb sautéed with\ngoat butter. Sweet with a hint of spice.",
   "Required Ingredient 1": "Stambulb",
   "Required Ingredient 2": "Goat Butter",
   "Required Ingredient 3": "-",
   "Required Ingredient 4": "-",
   "Required Ingredient 5": "-",
   "Cooking Method": "Cooking Pot"
 },
 {
   "Recipe #": 20,
   "Name": "Copious Mushroom Skewers",
   "Inventory Icon": "https://raw.githubusercontent.com/TOTKSheet/TOTKImages/main/Items/Item_Cook_B_13.png",
   "Caption": "Fans of fungal cuisine can't resist this simple\nmushroom-skewer dish. Very filling.",
   "Required Ingredient 1": "Mushroom",
   "Required Ingredient 2": "Mushroom",
   "Required Ingredient 3": "Mushroom",
   "Required Ingredient 4": "Mushroom",
   "Required Ingredient 5": "-",
   "Cooking Method": "Cooking Pot"
 },
 {
   "Recipe #": 21,
   "Name": "Spiced Meat Skewer",
   "Inventory Icon": "https://raw.githubusercontent.com/TOTKSheet/TOTKImages/main/Items/Item_Cook_P_03.png",
   "Caption": "A special Goron spice covers up the scent\nof the meat, allowing its flavor to shine.",
   "Required Ingredient 1": "Raw Meat",
   "Required Ingredient 2": "Goron Spice",
   "Required Ingredient 3": "-",
   "Required Ingredient 4": "-",
   "Required Ingredient 5": "-",
   "Cooking Method": "Cooking Pot"
 },
 {
   "Recipe #": 22,
   "Name": "Prime Spiced Meat Skewer",
   "Inventory Icon": "https://raw.githubusercontent.com/TOTKSheet/TOTKImages/main/Items/Item_Cook_P_04.png",
   "Caption": "The simple preparation of this steak dish\nbelies its complex taste profile.",
   "Required Ingredient 1": "Raw Prime Meat",
   "Required Ingredient 2": "Goron Spice",
   "Required Ingredient 3": "-",
   "Required Ingredient 4": "-",
   "Required Ingredient 5": "-",
   "Cooking Method": "Cooking Pot"
 },
 {
   "Recipe #": 23,
   "Name": "Gourmet Spiced Meat Skewer",
   "Inventory Icon": "https://raw.githubusercontent.com/TOTKSheet/TOTKImages/main/Items/Item_Cook_P_05.png",
   "Caption": "The rich aroma and juicy texture of this high-\nquality meat puts it in a league of its own.",
   "Required Ingredient 1": "Raw Gourmet Meat",
   "Required Ingredient 2": "Goron Spice",
   "Required Ingredient 3": "-",
   "Required Ingredient 4": "-",
   "Required Ingredient 5": "-",
   "Cooking Method": "Cooking Pot"
 },
 {
   "Recipe #": 24,
   "Name": "Crab Stir-Fry",
   "Inventory Icon": "https://raw.githubusercontent.com/TOTKSheet/TOTKImages/main/Items/Item_Cook_D_10.png",
   "Caption": "The Goron spice used in preparing this crab\npairs perfectly with the flavor of its meat.",
   "Required Ingredient 1": "Crab",
   "Required Ingredient 2": "Goron Spice",
   "Required Ingredient 3": "-",
   "Required Ingredient 4": "-",
   "Required Ingredient 5": "-",
   "Cooking Method": "Cooking Pot"
 },
 {
   "Recipe #": 25,
   "Name": "Meat and Seafood Fry",
   "Inventory Icon": "https://raw.githubusercontent.com/TOTKSheet/TOTKImages/main/Items/Item_Cook_B_17.png",
   "Caption": "A filling dish made by cooking fresh seafood\nand meat together.",
   "Required Ingredient 1": "Meat",
   "Required Ingredient 2": "Fish",
   "Required Ingredient 3": "-",
   "Required Ingredient 4": "-",
   "Required Ingredient 5": "-",
   "Cooking Method": "Cooking Pot"
 },
 {
   "Recipe #": 26,
   "Name": "Prime Meat and Seafood Fry",
   "Inventory Icon": "https://raw.githubusercontent.com/TOTKSheet/TOTKImages/main/Items/Item_Cook_B_18.png",
   "Caption": "This comfort dish is made with choice cuts\nof meat and seafood.",
   "Required Ingredient 1": "Tier 2 Meat",
   "Required Ingredient 2": "Fish",
   "Required Ingredient 3": "-",
   "Required Ingredient 4": "-",
   "Required Ingredient 5": "-",
   "Cooking Method": "Cooking Pot"
 },
 {
   "Recipe #": 27,
   "Name": "Gourmet Meat and Seafood Fry",
   "Inventory Icon": "https://raw.githubusercontent.com/TOTKSheet/TOTKImages/main/Items/Item_Cook_B_19.png",
   "Caption": "A marriage of the choicest cuts of meat and\nseafood. As delicious as it is filling!",
   "Required Ingredient 1": "Tier 3 Meat",
   "Required Ingredient 2": "Fish",
   "Required Ingredient 3": "-",
   "Required Ingredient 4": "-",
   "Required Ingredient 5": "-",
   "Cooking Method": "Cooking Pot"
 },
 {
   "Recipe #": 28,
   "Name": "Salt-Grilled Greens",
   "Inventory Icon": "https://raw.githubusercontent.com/TOTKSheet/TOTKImages/main/Items/Item_Cook_D_02.png",
   "Caption": "A health-boosting dish made with leafy\ngreens and a touch of salt.",
   "Required Ingredient 1": "Plant",
   "Required Ingredient 2": "Rock Salt",
   "Required Ingredient 3": "-",
   "Required Ingredient 4": "-",
   "Required Ingredient 5": "-",
   "Cooking Method": "Cooking Pot"
 },
 {
   "Recipe #": 29,
   "Name": "Salt-Grilled Mushrooms",
   "Inventory Icon": "https://raw.githubusercontent.com/TOTKSheet/TOTKImages/main/Items/Item_Cook_D_01.png",
   "Caption": "A basic mushroom dish made by lightly\nsalting mushrooms and grilling them.",
   "Required Ingredient 1": "Mushroom",
   "Required Ingredient 2": "Rock Salt",
   "Required Ingredient 3": "-",
   "Required Ingredient 4": "-",
   "Required Ingredient 5": "-",
   "Cooking Method": "Cooking Pot"
 },
 {
   "Recipe #": 30,
   "Name": "Salt-Grilled Meat",
   "Inventory Icon": "https://raw.githubusercontent.com/TOTKSheet/TOTKImages/main/Items/Item_Cook_D_04.png",
   "Caption": "Short on ingredients? Just rub some meat in\nsalt and cook it for a simple, tasty dish.",
   "Required Ingredient 1": "Tier 1 Meat",
   "Required Ingredient 2": "Rock Salt",
   "Required Ingredient 3": "-",
   "Required Ingredient 4": "-",
   "Required Ingredient 5": "-",
   "Cooking Method": "Cooking Pot"
 },
 {
   "Recipe #": 31,
   "Name": "Salt-Grilled Prime Meat",
   "Inventory Icon": "https://raw.githubusercontent.com/TOTKSheet/TOTKImages/main/Items/Item_Cook_D_05.png",
   "Caption": "A simple yet exquisite dish made by grilling\nhigh-quality meat on top of rock salt.",
   "Required Ingredient 1": "Tier 2 Meat",
   "Required Ingredient 2": "Rock Salt",
   "Required Ingredient 3": "-",
   "Required Ingredient 4": "-",
   "Required Ingredient 5": "-",
   "Cooking Method": "Cooking Pot"
 },
 {
   "Recipe #": 32,
   "Name": "Salt-Grilled Gourmet Meat",
   "Inventory Icon": "https://raw.githubusercontent.com/TOTKSheet/TOTKImages/main/Items/Item_Cook_D_06.png",
   "Caption": "This lavish grilled dish makes liberal use of\nhigh-quality cuts of meat.",
   "Required Ingredient 1": "Tier 3 Meat",
   "Required Ingredient 2": "Rock Salt",
   "Required Ingredient 3": "-",
   "Required Ingredient 4": "-",
   "Required Ingredient 5": "-",
   "Cooking Method": "Cooking Pot"
 },
 {
   "Recipe #": 33,
   "Name": "Salt-Grilled Fish",
   "Inventory Icon": "https://raw.githubusercontent.com/TOTKSheet/TOTKImages/main/Items/Item_Cook_D_03.png",
   "Caption": "A simple dish made by rolling a whole fish in\nnatural rock salt before grilling it.",
   "Required Ingredient 1": "Fish",
   "Required Ingredient 2": "Rock Salt",
   "Required Ingredient 3": "-",
   "Required Ingredient 4": "-",
   "Required Ingredient 5": "-",
   "Cooking Method": "Cooking Pot"
 },
 {
   "Recipe #": 34,
   "Name": "Salt-Grilled Crab",
   "Inventory Icon": "https://raw.githubusercontent.com/TOTKSheet/TOTKImages/main/Items/Item_Cook_D_09.png",
   "Caption": "Nine out of ten fishermen agree crab is best\nenjoyed grilled and with just a bit of salt.",
   "Required Ingredient 1": "Crab",
   "Required Ingredient 2": "Rock Salt",
   "Required Ingredient 3": "-",
   "Required Ingredient 4": "-",
   "Required Ingredient 5": "-",
   "Cooking Method": "Cooking Pot"
 },
 {
   "Recipe #": 35,
   "Name": "Herb Sauté",
   "Inventory Icon": "https://raw.githubusercontent.com/TOTKSheet/TOTKImages/main/Items/Item_Cook_P_02.png",
   "Caption": "A fragrant mixture of herbs and spices.\nIt's easily recognized by its unique aroma.",
   "Required Ingredient 1": "Plant",
   "Required Ingredient 2": "Goron Spice",
   "Required Ingredient 3": "-",
   "Required Ingredient 4": "-",
   "Required Ingredient 5": "-",
   "Cooking Method": "Cooking Pot"
 },
 {
   "Recipe #": 36,
   "Name": "Fragrant Mushroom Sauté",
   "Inventory Icon": "https://raw.githubusercontent.com/TOTKSheet/TOTKImages/main/Items/Item_Cook_P_01.png",
   "Caption": "The fragrant aroma of this sautéed spice and\nmushroom dish makes your mouth water.",
   "Required Ingredient 1": "Mushroom",
   "Required Ingredient 2": "Goron Spice",
   "Required Ingredient 3": "-",
   "Required Ingredient 4": "-",
   "Required Ingredient 5": "-",
   "Cooking Method": "Cooking Pot"
 },
 {
   "Recipe #": 37,
   "Name": "Pepper Steak",
   "Inventory Icon": "https://raw.githubusercontent.com/TOTKSheet/TOTKImages/main/Items/Item_Cook_D_07.png",
   "Caption": "The meat has been cooked in crushed\npeppers to accent its natural taste.",
   "Required Ingredient 1": "Meat",
   "Required Ingredient 2": "Spicy Pepper",
   "Required Ingredient 3": "-",
   "Required Ingredient 4": "-",
   "Required Ingredient 5": "-",
   "Cooking Method": "Cooking Pot"
 },
 {
   "Recipe #": 38,
   "Name": "Pepper Seafood",
   "Inventory Icon": "https://raw.githubusercontent.com/TOTKSheet/TOTKImages/main/Items/Item_Cook_D_08.png",
   "Caption": "The pepper seeds grilled with this seafood\ndraw out its taste and pleasant aroma.",
   "Required Ingredient 1": "Fish",
   "Required Ingredient 2": "Spicy Pepper",
   "Required Ingredient 3": "-",
   "Required Ingredient 4": "-",
   "Required Ingredient 5": "-",
   "Cooking Method": "Cooking Pot"
 },
 {
   "Recipe #": 39,
   "Name": "Fragrant Seafood Stew",
   "Inventory Icon": "https://raw.githubusercontent.com/TOTKSheet/TOTKImages/main/Items/Item_Cook_R_05.png",
   "Caption": "A tasty dish of seafood and stambulb cooked\nin oil. Its aroma will whet your appetite.",
   "Required Ingredient 1": "Fish",
   "Required Ingredient 2": "Stambulb",
   "Required Ingredient 3": "Oil Jar",
   "Required Ingredient 4": "-",
   "Required Ingredient 5": "-",
   "Cooking Method": "Cooking Pot"
 },
 {
   "Recipe #": 40,
   "Name": "Deep-Fried Drumstick",
   "Inventory Icon": "https://raw.githubusercontent.com/TOTKSheet/TOTKImages/main/Items/Item_Cook_R_06.png",
   "Caption": "A drumstick fried in high-quality oil. It's full of\nout-of-this-world flavor.",
   "Required Ingredient 1": "Raw Bird Drumstick",
   "Required Ingredient 2": "Oil Jar",
   "Required Ingredient 3": "-",
   "Required Ingredient 4": "-",
   "Required Ingredient 5": "-",
   "Cooking Method": "Cooking Pot"
 },
 {
   "Recipe #": 41,
   "Name": "Deep-Fried Thigh",
   "Inventory Icon": "https://raw.githubusercontent.com/TOTKSheet/TOTKImages/main/Items/Item_Cook_R_07.png",
   "Caption": "A deep-fried bird thigh so good, it's hard to\ntake bites that aren't too big!",
   "Required Ingredient 1": "Raw Bird Thigh",
   "Required Ingredient 2": "Oil Jar",
   "Required Ingredient 3": "-",
   "Required Ingredient 4": "-",
   "Required Ingredient 5": "-",
   "Cooking Method": "Cooking Pot"
 },
 {
   "Recipe #": 42,
   "Name": "Deep-Fried Bird Roast",
   "Inventory Icon": "https://raw.githubusercontent.com/TOTKSheet/TOTKImages/main/Items/Item_Cook_R_08.png",
   "Caption": "A deep-fried whole bird of the highest grade.\nIt's a standard item in any celebratory feast.",
   "Required Ingredient 1": "Raw Whole Bird",
   "Required Ingredient 2": "Oil Jar",
   "Required Ingredient 3": "-",
   "Required Ingredient 4": "-",
   "Required Ingredient 5": "-",
   "Cooking Method": "Cooking Pot"
 },
 {
   "Recipe #": 43,
   "Name": "Seafood Meunière",
   "Inventory Icon": "https://raw.githubusercontent.com/TOTKSheet/TOTKImages/main/Items/Item_Cook_H_01.png",
   "Caption": "Rich butter flanks fresh seafood. The secret\ningredient is lots and lots of love.",
   "Required Ingredient 1": "Fish",
   "Required Ingredient 2": "Goat Butter",
   "Required Ingredient 3": "Tabantha Wheat",
   "Required Ingredient 4": "-",
   "Required Ingredient 5": "-",
   "Cooking Method": "Cooking Pot"
 },
 {
   "Recipe #": 44,
   "Name": "Porgy Meunière",
   "Inventory Icon": "https://raw.githubusercontent.com/TOTKSheet/TOTKImages/main/Items/Item_Cook_H_02.png",
   "Caption": "Popular among residents of coastal regions,\nthis juicy porgy is a delish dish.",
   "Required Ingredient 1": "Porgy",
   "Required Ingredient 2": "Goat Butter",
   "Required Ingredient 3": "Tabantha Wheat",
   "Required Ingredient 4": "-",
   "Required Ingredient 5": "-",
   "Cooking Method": "Cooking Pot"
 },
 {
   "Recipe #": 45,
   "Name": "Salmon Meunière",
   "Inventory Icon": "https://raw.githubusercontent.com/TOTKSheet/TOTKImages/main/Items/Item_Cook_H_03.png",
   "Caption": "The crispy skin of this fried hearty salmon\nputs its texture in a class all its own.",
   "Required Ingredient 1": "Hearty Salmon",
   "Required Ingredient 2": "Goat Butter",
   "Required Ingredient 3": "Tabantha Wheat",
   "Required Ingredient 4": "-",
   "Required Ingredient 5": "-",
   "Cooking Method": "Cooking Pot"
 },
 {
   "Recipe #": 46,
   "Name": "Fruit and Mushroom Mix",
   "Inventory Icon": "https://raw.githubusercontent.com/TOTKSheet/TOTKImages/main/Items/Item_Cook_A_07.png",
   "Caption": "This dish contrasts the sweetness of fruit with\nthe savoriness of mushrooms.",
   "Required Ingredient 1": "Mushroom",
   "Required Ingredient 2": "Fruit",
   "Required Ingredient 3": "-",
   "Required Ingredient 4": "-",
   "Required Ingredient 5": "-",
   "Cooking Method": "Cooking Pot"
 },
 {
   "Recipe #": 47,
   "Name": "Simmered Fruit",
   "Inventory Icon": "https://raw.githubusercontent.com/TOTKSheet/TOTKImages/main/Items/Item_Cook_B_02.png",
   "Caption": "This sweet dish is made by heaping tasty\nfruits into a pan and simmering until tender.",
   "Required Ingredient 1": "Fruit",
   "Required Ingredient 2": "-",
   "Required Ingredient 3": "-",
   "Required Ingredient 4": "-",
   "Required Ingredient 5": "-",
   "Cooking Method": "Cooking Pot"
 },
 {
   "Recipe #": 48,
   "Name": "Copious Simmered Fruit",
   "Inventory Icon": "https://raw.githubusercontent.com/TOTKSheet/TOTKImages/main/Items/Item_Cook_B_12.png",
   "Caption": "The flavors of the various fruits in this\nsimmered dish exist in perfect harmony.",
   "Required Ingredient 1": "Fruit",
   "Required Ingredient 2": "Fruit",
   "Required Ingredient 3": "Fruit",
   "Required Ingredient 4": "Fruit",
   "Required Ingredient 5": "-",
   "Cooking Method": "Cooking Pot"
 },
 {
   "Recipe #": 49,
   "Name": "Simmered Tomato",
   "Inventory Icon": "https://raw.githubusercontent.com/TOTKSheet/TOTKImages/main/Items/Item_Cook_Q_01.png",
   "Caption": "When simmered until tender, nutritious\ntomatoes can give this dish a sour kick.",
   "Required Ingredient 1": "Hylian Tomato",
   "Required Ingredient 2": "-",
   "Required Ingredient 3": "-",
   "Required Ingredient 4": "-",
   "Required Ingredient 5": "-",
   "Cooking Method": "Cooking Pot"
 },
 {
   "Recipe #": 50,
   "Name": "Fruity Tomato Stew",
   "Inventory Icon": "https://raw.githubusercontent.com/TOTKSheet/TOTKImages/main/Items/Item_Cook_Q_02.png",
   "Caption": "A colorful dish, a bounty of fruit simmered\nwith fresh tomatoes.",
   "Required Ingredient 1": "Hylian Tomato",
   "Required Ingredient 2": "Fresh Milk",
   "Required Ingredient 3": "Rock Salt",
   "Required Ingredient 4": "-",
   "Required Ingredient 5": "-",
   "Cooking Method": "Cooking Pot"
 },
 {
   "Recipe #": 51,
   "Name": "Tomato Mushroom Stew",
   "Inventory Icon": "https://raw.githubusercontent.com/TOTKSheet/TOTKImages/main/Items/Item_Cook_Q_04.png",
   "Caption": "A dish of fragrant mushrooms simmered with\ntomato. Healthy and rich in fiber.",
   "Required Ingredient 1": "Mushroom",
   "Required Ingredient 2": "Hylian Tomato",
   "Required Ingredient 3": "-",
   "Required Ingredient 4": "-",
   "Required Ingredient 5": "-",
   "Cooking Method": "Cooking Pot"
 },
 {
   "Recipe #": 52,
   "Name": "Tomato Seafood Soup",
   "Inventory Icon": "https://raw.githubusercontent.com/TOTKSheet/TOTKImages/main/Items/Item_Cook_Q_05.png",
   "Caption": "Seafood simmered with tomato. Full of\nintense flavor.",
   "Required Ingredient 1": "Fish",
   "Required Ingredient 2": "Hylian Tomato",
   "Required Ingredient 3": "-",
   "Required Ingredient 4": "-",
   "Required Ingredient 5": "-",
   "Cooking Method": "Cooking Pot"
 },
 {
   "Recipe #": 53,
   "Name": "Cream of Vegetable Soup",
   "Inventory Icon": "https://raw.githubusercontent.com/TOTKSheet/TOTKImages/main/Items/Item_Cook_K_07.png",
   "Caption": "Made by simmering vegetables in milk, this\nhealthy dish is as simple as its ingredients.",
   "Required Ingredient 1": "Plant",
   "Required Ingredient 2": "Rock Salt",
   "Required Ingredient 3": "Fresh Milk",
   "Required Ingredient 4": "-",
   "Required Ingredient 5": "-",
   "Cooking Method": "Cooking Pot"
 },
 {
   "Recipe #": 54,
   "Name": "Veggie Cream Soup",
   "Inventory Icon": "https://raw.githubusercontent.com/TOTKSheet/TOTKImages/main/Items/Item_Cook_F_03.png",
   "Caption": "This creamy soup showcases the sweetness\nof vegetables in a veritable taste explosion.",
   "Required Ingredient 1": "Pumpkin or Carrot",
   "Required Ingredient 2": "Rock Salt",
   "Required Ingredient 3": "Fresh Milk",
   "Required Ingredient 4": "-",
   "Required Ingredient 5": "-",
   "Cooking Method": "Cooking Pot"
 },
 {
   "Recipe #": 55,
   "Name": "Cream of Mushroom Soup",
   "Inventory Icon": "https://raw.githubusercontent.com/TOTKSheet/TOTKImages/main/Items/Item_Cook_K_06.png",
   "Caption": "This creamy mushroom-and-vegetable soup\nis thick and flavorful. ",
   "Required Ingredient 1": "Mushroom",
   "Required Ingredient 2": "Plant",
   "Required Ingredient 3": "Rock Salt",
   "Required Ingredient 4": "Fresh Milk",
   "Required Ingredient 5": "-",
   "Cooking Method": "Cooking Pot"
 },
 {
   "Recipe #": 56,
   "Name": "Creamy Meat Soup",
   "Inventory Icon": "https://raw.githubusercontent.com/TOTKSheet/TOTKImages/main/Items/Item_Cook_F_01.png",
   "Caption": "This nutritious soup contains serious portions\nof lightly braised meat and many vegetables.",
   "Required Ingredient 1": "Meat",
   "Required Ingredient 2": "Plant",
   "Required Ingredient 3": "Rock Salt",
   "Required Ingredient 4": "Fresh Milk",
   "Required Ingredient 5": "-",
   "Cooking Method": "Cooking Pot"
 },
 {
   "Recipe #": 57,
   "Name": "Creamy Seafood Soup",
   "Inventory Icon": "https://raw.githubusercontent.com/TOTKSheet/TOTKImages/main/Items/Item_Cook_F_02.png",
   "Caption": "Thick-cut chunks of seafood and stock\nprovide a satisfying savoriness.",
   "Required Ingredient 1": "Fish",
   "Required Ingredient 2": "Plant",
   "Required Ingredient 3": "Rock Salt",
   "Required Ingredient 4": "Fresh Milk",
   "Required Ingredient 5": "-",
   "Cooking Method": "Cooking Pot"
 },
 {
   "Recipe #": 58,
   "Name": "Snail Chowder",
   "Inventory Icon": "https://raw.githubusercontent.com/TOTKSheet/TOTKImages/main/Items/Item_Cook_K_04.png",
   "Caption": "The pleasant texture and flavor of snails\ncombine with butter and milk in a rich soup.",
   "Required Ingredient 1": "Sneaky River Snail",
   "Required Ingredient 2": "Tabantha Wheat",
   "Required Ingredient 3": "Fresh Milk",
   "Required Ingredient 4": "Goat Butter",
   "Required Ingredient 5": "-",
   "Cooking Method": "Cooking Pot"
 },
 {
   "Recipe #": 59,
   "Name": "Creamy Heart Soup",
   "Inventory Icon": "https://raw.githubusercontent.com/TOTKSheet/TOTKImages/main/Items/Item_Cook_F_04.png",
   "Caption": "Enjoying this sweet soup with another person\nwill bring you both closer together.",
   "Required Ingredient 1": "Radish",
   "Required Ingredient 2": "Voltfruit",
   "Required Ingredient 3": "Hydromelon",
   "Required Ingredient 4": "Fresh Milk",
   "Required Ingredient 5": "-",
   "Cooking Method": "Cooking Pot"
 },
 {
   "Recipe #": 60,
   "Name": "Glazed Veggies",
   "Inventory Icon": "https://raw.githubusercontent.com/TOTKSheet/TOTKImages/main/Items/Item_Cook_A_14.png",
   "Caption": "Don't like the taste of vegetables? Simply\nsauté them in honey for a salty-sweet flavor!",
   "Required Ingredient 1": "Plant",
   "Required Ingredient 2": "Courser Bee Honey",
   "Required Ingredient 3": "-",
   "Required Ingredient 4": "-",
   "Required Ingredient 5": "-",
   "Cooking Method": "Cooking Pot"
 },
 {
   "Recipe #": 61,
   "Name": "Glazed Mushrooms",
   "Inventory Icon": "https://raw.githubusercontent.com/TOTKSheet/TOTKImages/main/Items/Item_Cook_A_11.png",
   "Caption": "The honey in this mushroom dish gives it a\nsweet, complex taste and a savory finish.",
   "Required Ingredient 1": "Mushroom",
   "Required Ingredient 2": "Courser Bee Honey",
   "Required Ingredient 3": "-",
   "Required Ingredient 4": "-",
   "Required Ingredient 5": "-",
   "Cooking Method": "Cooking Pot"
 },
 {
   "Recipe #": 62,
   "Name": "Glazed Meat",
   "Inventory Icon": "https://raw.githubusercontent.com/TOTKSheet/TOTKImages/main/Items/Item_Cook_A_12.png",
   "Caption": "The sweetness of the honey permeates the\nmeat, giving it a complex taste profile.",
   "Required Ingredient 1": "Meat",
   "Required Ingredient 2": "Courser Bee Honey",
   "Required Ingredient 3": "-",
   "Required Ingredient 4": "-",
   "Required Ingredient 5": "-",
   "Cooking Method": "Cooking Pot"
 },
 {
   "Recipe #": 63,
   "Name": "Glazed Seafood",
   "Inventory Icon": "https://raw.githubusercontent.com/TOTKSheet/TOTKImages/main/Items/Item_Cook_A_13.png",
   "Caption": "A seafood dish that you can actually\nwolf down whole!",
   "Required Ingredient 1": "Fish",
   "Required Ingredient 2": "Courser Bee Honey",
   "Required Ingredient 3": "-",
   "Required Ingredient 4": "-",
   "Required Ingredient 5": "-",
   "Cooking Method": "Cooking Pot"
 },
 {
   "Recipe #": 64,
   "Name": "Curry Rice",
   "Inventory Icon": "https://raw.githubusercontent.com/TOTKSheet/TOTKImages/main/Items/Item_Cook_J_01.png",
   "Caption": "A favorite all over Hyrule, this simple dish has\na flavor you just won't get tired of.",
   "Required Ingredient 1": "Hylian Rice",
   "Required Ingredient 2": "Goron Spice",
   "Required Ingredient 3": "-",
   "Required Ingredient 4": "-",
   "Required Ingredient 5": "-",
   "Cooking Method": "Cooking Pot"
 },
 {
   "Recipe #": 65,
   "Name": "Vegetable Curry",
   "Inventory Icon": "https://raw.githubusercontent.com/TOTKSheet/TOTKImages/main/Items/Item_Cook_J_02.png",
   "Caption": "This healthy curry is popular for its mild flavor\nand moderate spiciness.",
   "Required Ingredient 1": "Pumpkin or Carrot",
   "Required Ingredient 2": "Hylian Rice",
   "Required Ingredient 3": "Goron Spice",
   "Required Ingredient 4": "-",
   "Required Ingredient 5": "-",
   "Cooking Method": "Cooking Pot"
 },
 {
   "Recipe #": 66,
   "Name": "Meat Curry",
   "Inventory Icon": "https://raw.githubusercontent.com/TOTKSheet/TOTKImages/main/Items/Item_Cook_J_06.png",
   "Caption": "The heat from the spice allows you to enjoy\nthe large portion of the meat's savoriness.",
   "Required Ingredient 1": "Raw Meat",
   "Required Ingredient 2": "Hylian Rice",
   "Required Ingredient 3": "Goron Spice",
   "Required Ingredient 4": "-",
   "Required Ingredient 5": "-",
   "Cooking Method": "Cooking Pot"
 },
 {
   "Recipe #": 67,
   "Name": "Prime Meat Curry",
   "Inventory Icon": "https://raw.githubusercontent.com/TOTKSheet/TOTKImages/main/Items/Item_Cook_J_07.png",
   "Caption": "The high-quality meat in this curry has given\nit a deeper taste than most other curries.",
   "Required Ingredient 1": "Raw Prime Meat",
   "Required Ingredient 2": "Hylian Rice",
   "Required Ingredient 3": "Goron Spice",
   "Required Ingredient 4": "-",
   "Required Ingredient 5": "-",
   "Cooking Method": "Cooking Pot"
 },
 {
   "Recipe #": 68,
   "Name": "Gourmet Meat Curry",
   "Inventory Icon": "https://raw.githubusercontent.com/TOTKSheet/TOTKImages/main/Items/Item_Cook_J_09.png",
   "Caption": "The high-quality meat used in this prized\ndish satisfies meat and curry lovers alike.",
   "Required Ingredient 1": "Raw Gourmet Meat",
   "Required Ingredient 2": "Hylian Rice",
   "Required Ingredient 3": "Goron Spice",
   "Required Ingredient 4": "-",
   "Required Ingredient 5": "-",
   "Cooking Method": "Cooking Pot"
 },
 {
   "Recipe #": 69,
   "Name": "Poultry Curry",
   "Inventory Icon": "https://raw.githubusercontent.com/TOTKSheet/TOTKImages/main/Items/Item_Cook_J_04.png",
   "Caption": "The savory meat pairs well with the aroma\nof spice in this common curry.",
   "Required Ingredient 1": "Raw Bird Drumstick",
   "Required Ingredient 2": "Hylian Rice",
   "Required Ingredient 3": "Goron Spice",
   "Required Ingredient 4": "-",
   "Required Ingredient 5": "-",
   "Cooking Method": "Cooking Pot"
 },
 {
   "Recipe #": 70,
   "Name": "Prime Poultry Curry",
   "Inventory Icon": "https://raw.githubusercontent.com/TOTKSheet/TOTKImages/main/Items/Item_Cook_J_05.png",
   "Caption": "The secret to this curry's flavor is taking it off\nthe heat while you add the spices.",
   "Required Ingredient 1": "Raw Bird Thigh",
   "Required Ingredient 2": "Hylian Rice",
   "Required Ingredient 3": "Goron Spice",
   "Required Ingredient 4": "-",
   "Required Ingredient 5": "-",
   "Cooking Method": "Cooking Pot"
 },
 {
   "Recipe #": 71,
   "Name": "Gourmet Poultry Curry",
   "Inventory Icon": "https://raw.githubusercontent.com/TOTKSheet/TOTKImages/main/Items/Item_Cook_J_08.png",
   "Caption": "Once served in Hyrule Castle, the poultry\nused in this dish is of immensely high quality.",
   "Required Ingredient 1": "Raw Whole Bird",
   "Required Ingredient 2": "Hylian Rice",
   "Required Ingredient 3": "Goron Spice",
   "Required Ingredient 4": "-",
   "Required Ingredient 5": "-",
   "Cooking Method": "Cooking Pot"
 },
 {
   "Recipe #": 72,
   "Name": "Seafood Curry",
   "Inventory Icon": "https://raw.githubusercontent.com/TOTKSheet/TOTKImages/main/Items/Item_Cook_J_03.png",
   "Caption": "This dish brims with treasures from the sea.\nIts spice packs a kick, so it's not for kids.",
   "Required Ingredient 1": "Porgy",
   "Required Ingredient 2": "Hylian Rice",
   "Required Ingredient 3": "Goron Spice",
   "Required Ingredient 4": "-",
   "Required Ingredient 5": "-",
   "Cooking Method": "Cooking Pot"
 },
 {
   "Recipe #": 73,
   "Name": "Cheesy Curry",
   "Inventory Icon": "https://raw.githubusercontent.com/TOTKSheet/TOTKImages/main/Items/Item_Cook_S_01.png",
   "Caption": "Curry with plenty of Hateno cheese, which\nbalances the spiciness and urges seconds.",
   "Required Ingredient 1": "Hylian Rice",
   "Required Ingredient 2": "Hateno Cheese",
   "Required Ingredient 3": "Goron Spice",
   "Required Ingredient 4": "-",
   "Required Ingredient 5": "-",
   "Cooking Method": "Cooking Pot"
 },
 {
   "Recipe #": 74,
   "Name": "Carrot Stew",
   "Inventory Icon": "https://raw.githubusercontent.com/TOTKSheet/TOTKImages/main/Items/Item_Cook_K_08.png",
   "Caption": "This simple stew sat simmering for a long time\nto bring out the sweetness of the carrots.",
   "Required Ingredient 1": "Carrot",
   "Required Ingredient 2": "Goat Butter",
   "Required Ingredient 3": "Fresh Milk",
   "Required Ingredient 4": "Tabantha Wheat",
   "Required Ingredient 5": "-",
   "Cooking Method": "Cooking Pot"
 },
 {
   "Recipe #": 75,
   "Name": "Pumpkin Stew",
   "Inventory Icon": "https://raw.githubusercontent.com/TOTKSheet/TOTKImages/main/Items/Item_Cook_K_03.png",
   "Caption": "Simply simmer a pumpkin to make\nthis dish. A favorite in Kakariko Village.",
   "Required Ingredient 1": "Pumpkin",
   "Required Ingredient 2": "Tabantha Wheat",
   "Required Ingredient 3": "Fresh Milk",
   "Required Ingredient 4": "Goat Butter",
   "Required Ingredient 5": "-",
   "Cooking Method": "Cooking Pot"
 },
 {
   "Recipe #": 76,
   "Name": "Meat Stew",
   "Inventory Icon": "https://raw.githubusercontent.com/TOTKSheet/TOTKImages/main/Items/Item_Cook_K_01.png",
   "Caption": "The hearty meat in this mainstay dish leaves\nbellies satisfied all throughout Hyrule.",
   "Required Ingredient 1": "Tier 1 Meat",
   "Required Ingredient 2": "Tabantha Wheat",
   "Required Ingredient 3": "Fresh Milk",
   "Required Ingredient 4": "Goat Butter",
   "Required Ingredient 5": "-",
   "Cooking Method": "Cooking Pot"
 },
 {
   "Recipe #": 77,
   "Name": "Prime Meat Stew",
   "Inventory Icon": "https://raw.githubusercontent.com/TOTKSheet/TOTKImages/main/Items/Item_Cook_K_02.png",
   "Caption": "Letting the large portions of choice cuts of\nmeat simmer brought out their savoriness.",
   "Required Ingredient 1": "Tier 2 Meat",
   "Required Ingredient 2": "Tabantha Wheat",
   "Required Ingredient 3": "Fresh Milk",
   "Required Ingredient 4": "Goat Butter",
   "Required Ingredient 5": "-",
   "Cooking Method": "Cooking Pot"
 },
 {
   "Recipe #": 78,
   "Name": "Gourmet Meat Stew",
   "Inventory Icon": "https://raw.githubusercontent.com/TOTKSheet/TOTKImages/main/Items/Item_Cook_K_05.png",
   "Caption": "The meat has simmered for so long it melts in\nyour mouth. A true bucket-list meal!",
   "Required Ingredient 1": "Tier 3 Meat",
   "Required Ingredient 2": "Tabantha Wheat",
   "Required Ingredient 3": "Fresh Milk",
   "Required Ingredient 4": "Goat Butter",
   "Required Ingredient 5": "-",
   "Cooking Method": "Cooking Pot"
 },
 {
   "Recipe #": 79,
   "Name": "Meat-Stuffed Pumpkin",
   "Inventory Icon": "https://raw.githubusercontent.com/TOTKSheet/TOTKImages/main/Items/Item_Cook_B_20.png",
   "Caption": "This hollow, meat-filled pumpkin is a\nlocal specialty of Kakariko Village.",
   "Required Ingredient 1": "Pumpkin",
   "Required Ingredient 2": "Meat",
   "Required Ingredient 3": "-",
   "Required Ingredient 4": "-",
   "Required Ingredient 5": "-",
   "Cooking Method": "Cooking Pot"
 },
 {
   "Recipe #": 80,
   "Name": "Vegetable Risotto",
   "Inventory Icon": "https://raw.githubusercontent.com/TOTKSheet/TOTKImages/main/Items/Item_Cook_G_13.png",
   "Caption": "The sweetness of the ingredients\ngives this risotto a mild flavor.",
   "Required Ingredient 1": "Pumpkin or Carrot",
   "Required Ingredient 2": "Hylian Rice",
   "Required Ingredient 3": "Rock Salt",
   "Required Ingredient 4": "Goat Butter",
   "Required Ingredient 5": "-",
   "Cooking Method": "Cooking Pot"
 },
 {
   "Recipe #": 81,
   "Name": "Mushroom Risotto",
   "Inventory Icon": "https://raw.githubusercontent.com/TOTKSheet/TOTKImages/main/Items/Item_Cook_G_12.png",
   "Caption": "The tantalizing aroma of mushrooms and\nbutter beckons you to the table.",
   "Required Ingredient 1": "Mushroom",
   "Required Ingredient 2": "Hylian Rice",
   "Required Ingredient 3": "Rock Salt",
   "Required Ingredient 4": "Goat Butter",
   "Required Ingredient 5": "-",
   "Cooking Method": "Cooking Pot"
 },
 {
   "Recipe #": 82,
   "Name": "Salmon Risotto",
   "Inventory Icon": "https://raw.githubusercontent.com/TOTKSheet/TOTKImages/main/Items/Item_Cook_G_14.png",
   "Caption": "The rice used in this rich risotto permeates\nthe light flavor of the salmon.",
   "Required Ingredient 1": "Hearty Salmon",
   "Required Ingredient 2": "Hylian Rice",
   "Required Ingredient 3": "Rock Salt",
   "Required Ingredient 4": "Goat Butter",
   "Required Ingredient 5": "-",
   "Cooking Method": "Cooking Pot"
 },
 {
   "Recipe #": 83,
   "Name": "Crab Risotto",
   "Inventory Icon": "https://raw.githubusercontent.com/TOTKSheet/TOTKImages/main/Items/Item_Cook_G_17.png",
   "Caption": "An everyday staple of seaside villages, the\nsecret to its delicious flavor lies in crab fat.",
   "Required Ingredient 1": "Crab",
   "Required Ingredient 2": "Hylian Rice",
   "Required Ingredient 3": "Rock Salt",
   "Required Ingredient 4": "Goat Butter",
   "Required Ingredient 5": "-",
   "Cooking Method": "Cooking Pot"
 },
 {
   "Recipe #": 84,
   "Name": "Cheesy Risotto",
   "Inventory Icon": "https://raw.githubusercontent.com/TOTKSheet/TOTKImages/main/Items/Item_Cook_Q_10.png",
   "Caption": "Rich risotto made with fish or mushroom\nmixed with Hylian rice and Hateno cheese.",
   "Required Ingredient 1": "Fish / Mushroom / Plant",
   "Required Ingredient 2": "Hateno Cheese",
   "Required Ingredient 3": "Hylian Rice",
   "Required Ingredient 4": "Rock Salt",
   "Required Ingredient 5": "-",
   "Cooking Method": "Cooking Pot"
 },
 {
   "Recipe #": 85,
   "Name": "Poultry Pilaf",
   "Inventory Icon": "https://raw.githubusercontent.com/TOTKSheet/TOTKImages/main/Items/Item_Cook_E_01.png",
   "Caption": "Sautéed Hylian rice steamed in poultry\nbroth. Cook on low heat until the rice is fluffy.",
   "Required Ingredient 1": "Raw Bird Drumstick",
   "Required Ingredient 2": "Bird Egg",
   "Required Ingredient 3": "Hylian Rice",
   "Required Ingredient 4": "Goat Butter",
   "Required Ingredient 5": "-",
   "Cooking Method": "Cooking Pot"
 },
 {
   "Recipe #": 86,
   "Name": "Prime Poultry Pilaf",
   "Inventory Icon": "https://raw.githubusercontent.com/TOTKSheet/TOTKImages/main/Items/Item_Cook_E_02.png",
   "Caption": "The rice permeates the savory taste of the\npoultry in this Gerudo-region favorite.",
   "Required Ingredient 1": "Raw Bird Thigh",
   "Required Ingredient 2": "Bird Egg",
   "Required Ingredient 3": "Hylian Rice",
   "Required Ingredient 4": "Goat Butter",
   "Required Ingredient 5": "-",
   "Cooking Method": "Cooking Pot"
 },
 {
   "Recipe #": 87,
   "Name": "Gourmet Poultry Pilaf",
   "Inventory Icon": "https://raw.githubusercontent.com/TOTKSheet/TOTKImages/main/Items/Item_Cook_E_03.png",
   "Caption": "Made with the highest-quality poultry, every\nbite of this pilaf floods your mouth with flavor.",
   "Required Ingredient 1": "Raw Whole Bird",
   "Required Ingredient 2": "Bird Egg",
   "Required Ingredient 3": "Hylian Rice",
   "Required Ingredient 4": "Goat Butter",
   "Required Ingredient 5": "-",
   "Cooking Method": "Cooking Pot"
 },
 {
   "Recipe #": 88,
   "Name": "Seafood Paella",
   "Inventory Icon": "https://raw.githubusercontent.com/TOTKSheet/TOTKImages/main/Items/Item_Cook_N_01.png",
   "Caption": "No fisherman's birthday bash would be\ncomplete without this top-shelf seafood dish.",
   "Required Ingredient 1": "Porgy",
   "Required Ingredient 2": "Crab",
   "Required Ingredient 3": "Hylian Rice",
   "Required Ingredient 4": "Goat Butter",
   "Required Ingredient 5": "Rock Salt",
   "Cooking Method": "Cooking Pot"
 },
 {
   "Recipe #": 89,
   "Name": "Curry Pilaf",
   "Inventory Icon": "https://raw.githubusercontent.com/TOTKSheet/TOTKImages/main/Items/Item_Cook_G_11.png",
   "Caption": "The Goron spice used in this pilaf has given\nit a rich, spicy aroma.",
   "Required Ingredient 1": "Goron Spice",
   "Required Ingredient 2": "Hylian Rice",
   "Required Ingredient 3": "Goat Butter",
   "Required Ingredient 4": "-",
   "Required Ingredient 5": "-",
   "Cooking Method": "Cooking Pot"
 },
 {
   "Recipe #": 90,
   "Name": "Fried Egg and Rice",
   "Inventory Icon": "https://raw.githubusercontent.com/TOTKSheet/TOTKImages/main/Items/Item_Cook_E_04.png",
   "Caption": "The soft egg yolk pairs well with the fresh\nrice in this simple dish.",
   "Required Ingredient 1": "Hylian Rice",
   "Required Ingredient 2": "Bird Egg",
   "Required Ingredient 3": "-",
   "Required Ingredient 4": "-",
   "Required Ingredient 5": "-",
   "Cooking Method": "Cooking Pot"
 },
 {
   "Recipe #": 91,
   "Name": "Crunchy Fried Rice",
   "Inventory Icon": "https://raw.githubusercontent.com/TOTKSheet/TOTKImages/main/Items/Item_Cook_Q_08.png",
   "Caption": "Hylian rice fried up with meat in high-quality\noil. Each bite is packed with toasty flavor.",
   "Required Ingredient 1": "Meat",
   "Required Ingredient 2": "Oil Jar",
   "Required Ingredient 3": "Hylian Rice",
   "Required Ingredient 4": "Bird Egg",
   "Required Ingredient 5": "-",
   "Cooking Method": "Cooking Pot"
 },
 {
   "Recipe #": 92,
   "Name": "Seafood Fried Rice",
   "Inventory Icon": "https://raw.githubusercontent.com/TOTKSheet/TOTKImages/main/Items/Item_Cook_G_10.png",
   "Caption": "Various seafood has been sautéed with rice.\nThe stronger the flame, the tastier the dish!",
   "Required Ingredient 1": "Porgy",
   "Required Ingredient 2": "Hylian Rice",
   "Required Ingredient 3": "Rock Salt",
   "Required Ingredient 4": "-",
   "Required Ingredient 5": "-",
   "Cooking Method": "Cooking Pot"
 },
 {
   "Recipe #": 93,
   "Name": "Crab Omelet with Rice",
   "Inventory Icon": "https://raw.githubusercontent.com/TOTKSheet/TOTKImages/main/Items/Item_Cook_G_16.png",
   "Caption": "The fluffy crab legs pair perfectly with the\nrice for a truly scrumptious dish.",
   "Required Ingredient 1": "Crab",
   "Required Ingredient 2": "Bird Egg",
   "Required Ingredient 3": "Hylian Rice",
   "Required Ingredient 4": "Rock Salt",
   "Required Ingredient 5": "-",
   "Cooking Method": "Cooking Pot"
 },
 {
   "Recipe #": 94,
   "Name": "Meat and Rice Bowl",
   "Inventory Icon": "https://raw.githubusercontent.com/TOTKSheet/TOTKImages/main/Items/Item_Cook_G_05.png",
   "Caption": "This dish of rice and lightly seared meat is a\nmainstay all throughout Hyrule.",
   "Required Ingredient 1": "Raw Meat",
   "Required Ingredient 2": "Hylian Rice",
   "Required Ingredient 3": "Rock Salt",
   "Required Ingredient 4": "-",
   "Required Ingredient 5": "-",
   "Cooking Method": "Cooking Pot"
 },
 {
   "Recipe #": 95,
   "Name": "Prime Meat and Rice Bowl",
   "Inventory Icon": "https://raw.githubusercontent.com/TOTKSheet/TOTKImages/main/Items/Item_Cook_G_06.png",
   "Caption": "This bowl is loaded with high-quality meat.\nYour hunt for a serious meal ends here.",
   "Required Ingredient 1": "Raw Prime Meat",
   "Required Ingredient 2": "Hylian Rice",
   "Required Ingredient 3": "Rock Salt",
   "Required Ingredient 4": "-",
   "Required Ingredient 5": "-",
   "Cooking Method": "Cooking Pot"
 },
 {
   "Recipe #": 96,
   "Name": "Gourmet Meat and Rice Bowl",
   "Inventory Icon": "https://raw.githubusercontent.com/TOTKSheet/TOTKImages/main/Items/Item_Cook_G_09.png",
   "Caption": "Only the most carefully selected cuts of high-\nquality meats go into this dish.",
   "Required Ingredient 1": "Raw Gourmet Meat",
   "Required Ingredient 2": "Hylian Rice",
   "Required Ingredient 3": "Rock Salt",
   "Required Ingredient 4": "-",
   "Required Ingredient 5": "-",
   "Cooking Method": "Cooking Pot"
 },
 {
   "Recipe #": 97,
   "Name": "Cheesy Meat Bowl",
   "Inventory Icon": "https://raw.githubusercontent.com/TOTKSheet/TOTKImages/main/Items/Item_Cook_S_02.png",
   "Caption": "A high-calorie dish with meat and plenty of\ncheese. A great dish for very hungry diners.",
   "Required Ingredient 1": "Raw Meat",
   "Required Ingredient 2": "Hylian Rice",
   "Required Ingredient 3": "Hateno Cheese",
   "Required Ingredient 4": "Rock Salt",
   "Required Ingredient 5": "-",
   "Cooking Method": "Cooking Pot"
 },
 {
   "Recipe #": 98,
   "Name": "Prime Cheesy Meat Bowl",
   "Inventory Icon": "https://raw.githubusercontent.com/TOTKSheet/TOTKImages/main/Items/Item_Cook_S_03.png",
   "Caption": "This bowl is loaded with high-quality meat and\ncheese. A satisfying meal for any big eater.",
   "Required Ingredient 1": "Raw Prime Meat",
   "Required Ingredient 2": "Hylian Rice",
   "Required Ingredient 3": "Hateno Cheese",
   "Required Ingredient 4": "Rock Salt",
   "Required Ingredient 5": "-",
   "Cooking Method": "Cooking Pot"
 },
 {
   "Recipe #": 99,
   "Name": "Gourmet Cheesy Meat Bowl",
   "Inventory Icon": "https://raw.githubusercontent.com/TOTKSheet/TOTKImages/main/Items/Item_Cook_S_04.png",
   "Caption": "Top-quality meat and cheese piled high. But\ncan it satisfy the ultimate gourmand?",
   "Required Ingredient 1": "Raw Gourmet Meat",
   "Required Ingredient 2": "Hylian Rice",
   "Required Ingredient 3": "Hateno Cheese",
   "Required Ingredient 4": "Rock Salt",
   "Required Ingredient 5": "-",
   "Cooking Method": "Cooking Pot"
 },
 {
   "Recipe #": 100,
   "Name": "Veggie Rice Balls",
   "Inventory Icon": "https://raw.githubusercontent.com/TOTKSheet/TOTKImages/main/Items/Item_Cook_G_03.png",
   "Caption": "This home-style dish of Kakariko Village is\nstuffed with the bounty of the mountains.",
   "Required Ingredient 1": "Plant",
   "Required Ingredient 2": "Hylian Rice",
   "Required Ingredient 3": "-",
   "Required Ingredient 4": "-",
   "Required Ingredient 5": "-",
   "Cooking Method": "Cooking Pot"
 },
 {
   "Recipe #": 101,
   "Name": "Mushroom Rice Balls",
   "Inventory Icon": "https://raw.githubusercontent.com/TOTKSheet/TOTKImages/main/Items/Item_Cook_G_04.png",
   "Caption": "The aroma of the mushrooms tickles your\nnose as you peel back the leafy wrapping.",
   "Required Ingredient 1": "Mushroom",
   "Required Ingredient 2": "Hylian Rice",
   "Required Ingredient 3": "-",
   "Required Ingredient 4": "-",
   "Required Ingredient 5": "-",
   "Cooking Method": "Cooking Pot"
 },
 {
   "Recipe #": 102,
   "Name": "Meaty Rice Balls",
   "Inventory Icon": "https://raw.githubusercontent.com/TOTKSheet/TOTKImages/main/Items/Item_Cook_G_15.png",
   "Caption": "The sweet and spicy meat stuffed into these\nrice balls will keep you full for some time.",
   "Required Ingredient 1": "Meat",
   "Required Ingredient 2": "Hylian Rice",
   "Required Ingredient 3": "-",
   "Required Ingredient 4": "-",
   "Required Ingredient 5": "-",
   "Cooking Method": "Cooking Pot"
 },
 {
   "Recipe #": 103,
   "Name": "Seafood Rice Balls",
   "Inventory Icon": "https://raw.githubusercontent.com/TOTKSheet/TOTKImages/main/Items/Item_Cook_G_02.png",
   "Caption": "Stuffed with aromatic seafood, the flavor can\nvary by ingredients but never disappoints.",
   "Required Ingredient 1": "Fish",
   "Required Ingredient 2": "Hylian Rice",
   "Required Ingredient 3": "-",
   "Required Ingredient 4": "-",
   "Required Ingredient 5": "-",
   "Cooking Method": "Cooking Pot"
 },
 {
   "Recipe #": 104,
   "Name": "Veggie Porridge",
   "Inventory Icon": "https://raw.githubusercontent.com/TOTKSheet/TOTKImages/main/Items/Item_Cook_R_02.png",
   "Caption": "Porridge made of easy-to-digest vegetables,\nfresh milk, and Hylian rice. An uplifting dish.",
   "Required Ingredient 1": "Plant",
   "Required Ingredient 2": "Hylian Rice",
   "Required Ingredient 3": "Fresh Milk",
   "Required Ingredient 4": "-",
   "Required Ingredient 5": "-",
   "Cooking Method": "Cooking Pot"
 },
 {
   "Recipe #": 105,
   "Name": "Wheat Bread",
   "Inventory Icon": "https://raw.githubusercontent.com/TOTKSheet/TOTKImages/main/Items/Item_Cook_M_01.png",
   "Caption": "Made with wheat from the Tabantha region,\nthis soft, springy bread smells just heavenly.",
   "Required Ingredient 1": "Tabantha Wheat",
   "Required Ingredient 2": "Rock Salt",
   "Required Ingredient 3": "-",
   "Required Ingredient 4": "-",
   "Required Ingredient 5": "-",
   "Cooking Method": "Cooking Pot"
 },
 {
   "Recipe #": 106,
   "Name": "Melty Cheesy Bread",
   "Inventory Icon": "https://raw.githubusercontent.com/TOTKSheet/TOTKImages/main/Items/Item_Cook_R_09.png",
   "Caption": "Is there anything better than a simple slice of\nbread baked with Hateno cheese on top?",
   "Required Ingredient 1": "Tabantha Wheat",
   "Required Ingredient 2": "Hateno Cheese",
   "Required Ingredient 3": "-",
   "Required Ingredient 4": "-",
   "Required Ingredient 5": "-",
   "Cooking Method": "Cooking Pot"
 },
 {
   "Recipe #": 107,
   "Name": "Hylian Tomato Pizza",
   "Inventory Icon": "https://raw.githubusercontent.com/TOTKSheet/TOTKImages/main/Items/Item_Cook_R_04.png",
   "Caption": "A pizza made with fresh Hylian tomato. Slices\nof melty Hateno cheese make it irresistible.",
   "Required Ingredient 1": "Hylian Tomato",
   "Required Ingredient 2": "Tabantha Wheat",
   "Required Ingredient 3": "Hateno Cheese",
   "Required Ingredient 4": "-",
   "Required Ingredient 5": "-",
   "Cooking Method": "Cooking Pot"
 },
 {
   "Recipe #": 108,
   "Name": "Meat Pie",
   "Inventory Icon": "https://raw.githubusercontent.com/TOTKSheet/TOTKImages/main/Items/Item_Cook_I_04.png",
   "Caption": "You'll need an extra napkin to deal with this\njuicy pie of perfectly baked minced meat.",
   "Required Ingredient 1": "Meat",
   "Required Ingredient 2": "Tabantha Wheat",
   "Required Ingredient 3": "Goat Butter",
   "Required Ingredient 4": "Rock Salt",
   "Required Ingredient 5": "-",
   "Cooking Method": "Cooking Pot"
 },
 {
   "Recipe #": 109,
   "Name": "Fish Pie",
   "Inventory Icon": "https://raw.githubusercontent.com/TOTKSheet/TOTKImages/main/Items/Item_Cook_I_15.png",
   "Caption": "A mainstay in any fisherman's home, the\ncrisp crust pairs well with the fishy flavor.",
   "Required Ingredient 1": "Fish",
   "Required Ingredient 2": "Tabantha Wheat",
   "Required Ingredient 3": "Goat Butter",
   "Required Ingredient 4": "Rock Salt",
   "Required Ingredient 5": "-",
   "Cooking Method": "Cooking Pot"
 },
 {
   "Recipe #": 110,
   "Name": "Cheesy Tomato",
   "Inventory Icon": "https://raw.githubusercontent.com/TOTKSheet/TOTKImages/main/Items/Item_Cook_S_10.png",
   "Caption": "A simple dish of Hylian tomato topped with\ndelicious Hateno cheese. A perfect snack.",
   "Required Ingredient 1": "Hylian Tomato",
   "Required Ingredient 2": "Hateno Cheese",
   "Required Ingredient 3": "-",
   "Required Ingredient 4": "-",
   "Required Ingredient 5": "-",
   "Cooking Method": "Cooking Pot"
 },
 {
   "Recipe #": 111,
   "Name": "Cheesy Baked Fish",
   "Inventory Icon": "https://raw.githubusercontent.com/TOTKSheet/TOTKImages/main/Items/Item_Cook_R_10.png",
   "Caption": "Fresh seafood delightfully accented with a\ngenerous serving of Hateno cheese.",
   "Required Ingredient 1": "Fish",
   "Required Ingredient 2": "Hateno Cheese",
   "Required Ingredient 3": "-",
   "Required Ingredient 4": "-",
   "Required Ingredient 5": "-",
   "Cooking Method": "Cooking Pot"
 },
 {
   "Recipe #": 112,
   "Name": "Omelet",
   "Inventory Icon": "https://raw.githubusercontent.com/TOTKSheet/TOTKImages/main/Items/Item_Cook_A_10.png",
   "Caption": "This simple dish is common all over Hyrule.\nSimply fry egg until it's nice and plump.",
   "Required Ingredient 1": "Bird Egg",
   "Required Ingredient 2": "-",
   "Required Ingredient 3": "-",
   "Required Ingredient 4": "-",
   "Required Ingredient 5": "-",
   "Cooking Method": "Cooking Pot"
 },
 {
   "Recipe #": 113,
   "Name": "Vegetable Omelet",
   "Inventory Icon": "https://raw.githubusercontent.com/TOTKSheet/TOTKImages/main/Items/Item_Cook_N_03.png",
   "Caption": "This home-style dish mixes fluffy eggs with\nchopped vegetables for nutritional balance.",
   "Required Ingredient 1": "Plant",
   "Required Ingredient 2": "Bird Egg",
   "Required Ingredient 3": "Goat Butter",
   "Required Ingredient 4": "Rock Salt",
   "Required Ingredient 5": "-",
   "Cooking Method": "Cooking Pot"
 },
 {
   "Recipe #": 114,
   "Name": "Mushroom Omelet",
   "Inventory Icon": "https://raw.githubusercontent.com/TOTKSheet/TOTKImages/main/Items/Item_Cook_N_04.png",
   "Caption": "The fluffy texture of this omelet is one of the\ngreat joys of this dish, as well as life.",
   "Required Ingredient 1": "Mushroom",
   "Required Ingredient 2": "Bird Egg",
   "Required Ingredient 3": "Rock Salt",
   "Required Ingredient 4": "Goat Butter",
   "Required Ingredient 5": "-",
   "Cooking Method": "Cooking Pot"
 },
 {
   "Recipe #": 115,
   "Name": "Cheesy Omelet",
   "Inventory Icon": "https://raw.githubusercontent.com/TOTKSheet/TOTKImages/main/Items/Item_Cook_R_01.png",
   "Caption": "A satisfying dish with Hateno cheese poured\nover a tasty omelet.",
   "Required Ingredient 1": "Mushroom / Plant",
   "Required Ingredient 2": "Hateno Cheese",
   "Required Ingredient 3": "Bird Egg",
   "Required Ingredient 4": "Rock Salt",
   "Required Ingredient 5": "-",
   "Cooking Method": "Cooking Pot"
 },
 {
   "Recipe #": 116,
   "Name": "Hot Buttered Apple",
   "Inventory Icon": "https://raw.githubusercontent.com/TOTKSheet/TOTKImages/main/Items/Item_Cook_I_07.png",
   "Caption": "The apple's sweetness has been enhanced\nby smothering it with butter and baking it.",
   "Required Ingredient 1": "Apple / Golden Apple",
   "Required Ingredient 2": "Goat Butter",
   "Required Ingredient 3": "-",
   "Required Ingredient 4": "-",
   "Required Ingredient 5": "-",
   "Cooking Method": "Cooking Pot"
 },
 {
   "Recipe #": 117,
   "Name": "Honeyed Fruits",
   "Inventory Icon": "https://raw.githubusercontent.com/TOTKSheet/TOTKImages/main/Items/Item_Cook_I_09.png",
   "Caption": "A dish that combines the thick sweetness of\nhoney with the acidity of sour fruits.",
   "Required Ingredient 1": "Fruit",
   "Required Ingredient 2": "Courser Bee Honey",
   "Required Ingredient 3": "-",
   "Required Ingredient 4": "-",
   "Required Ingredient 5": "-",
   "Cooking Method": "Cooking Pot"
 },
 {
   "Recipe #": 118,
   "Name": "Honeyed Apple",
   "Inventory Icon": "https://raw.githubusercontent.com/TOTKSheet/TOTKImages/main/Items/Item_Cook_I_08.png",
   "Caption": "A juicy sweet-and-sour dish combining\nnewly ripened apples with honey. ",
   "Required Ingredient 1": "Apple / Golden Apple",
   "Required Ingredient 2": "Courser Bee Honey",
   "Required Ingredient 3": "-",
   "Required Ingredient 4": "-",
   "Required Ingredient 5": "-",
   "Cooking Method": "Cooking Pot"
 },
 {
   "Recipe #": 119,
   "Name": "Honey Candy",
   "Inventory Icon": "https://raw.githubusercontent.com/TOTKSheet/TOTKImages/main/Items/Item_Cook_I_16.png",
   "Caption": "A natural sweet, brimming with nutrition and\nmade by stewing fresh honey.",
   "Required Ingredient 1": "Courser Bee Honey",
   "Required Ingredient 2": "-",
   "Required Ingredient 3": "-",
   "Required Ingredient 4": "-",
   "Required Ingredient 5": "-",
   "Cooking Method": "Cooking Pot"
 },
 {
   "Recipe #": 120,
   "Name": "Fried Bananas",
   "Inventory Icon": "https://raw.githubusercontent.com/TOTKSheet/TOTKImages/main/Items/Item_Cook_I_13.png",
   "Caption": "Children love fried mighty bananas. The trick\nis frying them over very high heat.",
   "Required Ingredient 1": "Mighty Bananas",
   "Required Ingredient 2": "Tabantha Wheat",
   "Required Ingredient 3": "Cane Sugar",
   "Required Ingredient 4": "-",
   "Required Ingredient 5": "-",
   "Cooking Method": "Cooking Pot"
 },
 {
   "Recipe #": 121,
   "Name": "Egg Pudding",
   "Inventory Icon": "https://raw.githubusercontent.com/TOTKSheet/TOTKImages/main/Items/Item_Cook_I_14.png",
   "Caption": "Made by cooking eggs and milk in a special\nmold, its soft texture melts in your mouth.",
   "Required Ingredient 1": "Bird Egg",
   "Required Ingredient 2": "Fresh Milk",
   "Required Ingredient 3": "Cane Sugar",
   "Required Ingredient 4": "-",
   "Required Ingredient 5": "-",
   "Cooking Method": "Cooking Pot"
 },
 {
   "Recipe #": 122,
   "Name": "Plain Crepe",
   "Inventory Icon": "https://raw.githubusercontent.com/TOTKSheet/TOTKImages/main/Items/Item_Cook_I_10.png",
   "Caption": "The simplicity of this dish lets the flavor of its\ningredients shine.",
   "Required Ingredient 1": "Tabantha Wheat",
   "Required Ingredient 2": "Fresh Milk",
   "Required Ingredient 3": "Bird Egg",
   "Required Ingredient 4": "Cane Sugar",
   "Required Ingredient 5": "-",
   "Cooking Method": "Cooking Pot"
 },
 {
   "Recipe #": 123,
   "Name": "Wildberry Crepe",
   "Inventory Icon": "https://raw.githubusercontent.com/TOTKSheet/TOTKImages/main/Items/Item_Cook_I_11.png",
   "Caption": "Sweet, tart wildberries are folded into thin,\nspringy dough to make this dessert.",
   "Required Ingredient 1": "Tabantha Wheat",
   "Required Ingredient 2": "Fresh Milk",
   "Required Ingredient 3": "Bird Egg",
   "Required Ingredient 4": "Cane Sugar",
   "Required Ingredient 5": "Wildberry",
   "Cooking Method": "Cooking Pot"
 },
 {
   "Recipe #": 124,
   "Name": "Honey Crepe",
   "Inventory Icon": "https://raw.githubusercontent.com/TOTKSheet/TOTKImages/main/Items/Item_Cook_I_17.png",
   "Caption": "Honey has been drizzled over thin crepes to\nbring out their natural sweetness and flavor.",
   "Required Ingredient 1": "Tabantha Wheat",
   "Required Ingredient 2": "Fresh Milk",
   "Required Ingredient 3": "Bird Egg",
   "Required Ingredient 4": "Cane Sugar",
   "Required Ingredient 5": "Courser Bee Honey",
   "Cooking Method": "Cooking Pot"
 },
 {
   "Recipe #": 125,
   "Name": "Nutcake",
   "Inventory Icon": "https://raw.githubusercontent.com/TOTKSheet/TOTKImages/main/Items/Item_Cook_I_12.png",
   "Caption": "Forest nuts give this cake a pleasant texture\nand a simple, understated sweetness.",
   "Required Ingredient 1": "Tabantha Wheat",
   "Required Ingredient 2": "Goat Butter",
   "Required Ingredient 3": "Cane Sugar",
   "Required Ingredient 4": "Nut",
   "Required Ingredient 5": "-",
   "Cooking Method": "Cooking Pot"
 },
 {
   "Recipe #": 126,
   "Name": "Fruitcake",
   "Inventory Icon": "https://raw.githubusercontent.com/TOTKSheet/TOTKImages/main/Items/Item_Cook_N_02.png",
   "Caption": "Making ample use of fruits found all over\nHyrule, this cake is a must for celebrations.",
   "Required Ingredient 1": "Dessert Fruit",
   "Required Ingredient 2": "Apple or Wildberry",
   "Required Ingredient 3": "Tabantha Wheat",
   "Required Ingredient 4": "Cane Sugar",
   "Required Ingredient 5": "-",
   "Cooking Method": "Cooking Pot"
 },
 {
   "Recipe #": 127,
   "Name": "Carrot Cake",
   "Inventory Icon": "https://raw.githubusercontent.com/TOTKSheet/TOTKImages/main/Items/Item_Cook_I_05.png",
   "Caption": "Even those who don't like carrots tend to\nenjoy the mild sweetness of this cake.",
   "Required Ingredient 1": "Carrot",
   "Required Ingredient 2": "Tabantha Wheat",
   "Required Ingredient 3": "Cane Sugar",
   "Required Ingredient 4": "Goat Butter",
   "Required Ingredient 5": "-",
   "Cooking Method": "Cooking Pot"
 },
 {
   "Recipe #": 128,
   "Name": "Pumpkin Pie",
   "Inventory Icon": "https://raw.githubusercontent.com/TOTKSheet/TOTKImages/main/Items/Item_Cook_I_06.png",
   "Caption": "The intense sweetness of pumpkins makes\nthis dessert popular among children.",
   "Required Ingredient 1": "Pumpkin",
   "Required Ingredient 2": "Tabantha Wheat",
   "Required Ingredient 3": "Cane Sugar",
   "Required Ingredient 4": "Goat Butter",
   "Required Ingredient 5": "-",
   "Cooking Method": "Cooking Pot"
 },
 {
   "Recipe #": 129,
   "Name": "Cheesecake",
   "Inventory Icon": "https://raw.githubusercontent.com/TOTKSheet/TOTKImages/main/Items/Item_Cook_Q_09.png",
   "Caption": "A rich, moist, flavorful dessert with a\nHateno cheese base.",
   "Required Ingredient 1": "Hateno Cheese",
   "Required Ingredient 2": "Tabantha Wheat",
   "Required Ingredient 3": "Cane Sugar",
   "Required Ingredient 4": "-",
   "Required Ingredient 5": "-",
   "Cooking Method": "Cooking Pot"
 },
 {
   "Recipe #": 130,
   "Name": "Fruit Pie",
   "Inventory Icon": "https://raw.githubusercontent.com/TOTKSheet/TOTKImages/main/Items/Item_Cook_I_01.png",
   "Caption": "A celebration isn't a celebration until this\nfruit-filled crust hits the table!",
   "Required Ingredient 1": "Fruit",
   "Required Ingredient 2": "Tabantha Wheat",
   "Required Ingredient 3": "Goat Butter",
   "Required Ingredient 4": "Cane Sugar",
   "Required Ingredient 5": "-",
   "Cooking Method": "Cooking Pot"
 },
 {
   "Recipe #": 131,
   "Name": "Apple Pie",
   "Inventory Icon": "https://raw.githubusercontent.com/TOTKSheet/TOTKImages/main/Items/Item_Cook_I_02.png",
   "Caption": "The crispy, flaky pie crust and sweet apples\nare a match made in heaven.",
   "Required Ingredient 1": "Apple / Golden Apple",
   "Required Ingredient 2": "Tabantha Wheat",
   "Required Ingredient 3": "Goat Butter",
   "Required Ingredient 4": "Cane Sugar",
   "Required Ingredient 5": "-",
   "Cooking Method": "Cooking Pot"
 },
 {
   "Recipe #": 132,
   "Name": "Egg Tart",
   "Inventory Icon": "https://raw.githubusercontent.com/TOTKSheet/TOTKImages/main/Items/Item_Cook_I_03.png",
   "Caption": "You'll know this simple dessert is done\nbaking when it smells just delightful.",
   "Required Ingredient 1": "Bird Egg",
   "Required Ingredient 2": "Tabantha Wheat",
   "Required Ingredient 3": "Goat Butter",
   "Required Ingredient 4": "Cane Sugar",
   "Required Ingredient 5": "-",
   "Cooking Method": "Cooking Pot"
 },
 {
   "Recipe #": 133,
   "Name": "Milk",
   "Inventory Icon": "https://raw.githubusercontent.com/TOTKSheet/TOTKImages/main/Items/Item_Cook_K_09.png",
   "Caption": "Make this by heating up some milk. Drink it\nbefore bed to ensure a good night's sleep.",
   "Required Ingredient 1": "Fresh Milk",
   "Required Ingredient 2": "-",
   "Required Ingredient 3": "-",
   "Required Ingredient 4": "-",
   "Required Ingredient 5": "-",
   "Cooking Method": "Cooking Pot"
 },
 {
   "Recipe #": 134,
   "Name": "Noble Pursuit",
   "Inventory Icon": "https://raw.githubusercontent.com/TOTKSheet/TOTKImages/main/Items/Item_Cook_R_03.png",
   "Caption": "A popular fruit juice in Gerudo Town. Its\ntropical flavor will cheer you right up.",
   "Required Ingredient 1": "Palm Fruit",
   "Required Ingredient 2": "Hydromelon",
   "Required Ingredient 3": "Voltfruit",
   "Required Ingredient 4": "Rock Salt",
   "Required Ingredient 5": "-",
   "Cooking Method": "Cooking Pot"
 },
 {
   "Recipe #": 135,
   "Name": "Monster Stew",
   "Inventory Icon": "https://raw.githubusercontent.com/TOTKSheet/TOTKImages/main/Items/Item_Cook_L_01.png",
   "Caption": "Meat and seafood simmered in monster\nextract. A savory dish despite its ingredients.",
   "Required Ingredient 1": "Meat",
   "Required Ingredient 2": "Fish",
   "Required Ingredient 3": "Monster Extract",
   "Required Ingredient 4": "-",
   "Required Ingredient 5": "-",
   "Cooking Method": "Cooking Pot"
 },
 {
   "Recipe #": 136,
   "Name": "Monster Soup",
   "Inventory Icon": "https://raw.githubusercontent.com/TOTKSheet/TOTKImages/main/Items/Item_Cook_L_02.png",
   "Caption": "Using monster extract as a base, this soup's\ndistinct gaminess is either loved or hated.",
   "Required Ingredient 1": "Tabantha Wheat",
   "Required Ingredient 2": "Goat Butter",
   "Required Ingredient 3": "Fresh Milk",
   "Required Ingredient 4": "Monster Extract",
   "Required Ingredient 5": "-",
   "Cooking Method": "Cooking Pot"
 },
 {
   "Recipe #": 137,
   "Name": "Monster Curry",
   "Inventory Icon": "https://raw.githubusercontent.com/TOTKSheet/TOTKImages/main/Items/Item_Cook_L_05.png",
   "Caption": "This unusual take on curry uses monster\nextract and doesn't rely only on spices.",
   "Required Ingredient 1": "Hylian Rice",
   "Required Ingredient 2": "Goron Spice",
   "Required Ingredient 3": "Monster Extract",
   "Required Ingredient 4": "-",
   "Required Ingredient 5": "-",
   "Cooking Method": "Cooking Pot"
 },
 {
   "Recipe #": 138,
   "Name": "Monster Rice Balls",
   "Inventory Icon": "https://raw.githubusercontent.com/TOTKSheet/TOTKImages/main/Items/Item_Cook_L_04.png",
   "Caption": "Rice balls flavored with monster extract.\nTheir unique aroma is not for everyone.",
   "Required Ingredient 1": "Hylian Rice",
   "Required Ingredient 2": "Rock Salt",
   "Required Ingredient 3": "Monster Extract",
   "Required Ingredient 4": "-",
   "Required Ingredient 5": "-",
   "Cooking Method": "Cooking Pot"
 },
 {
   "Recipe #": 139,
   "Name": "Monster Cake",
   "Inventory Icon": "https://raw.githubusercontent.com/TOTKSheet/TOTKImages/main/Items/Item_Cook_L_03.png",
   "Caption": "It's said that once you have a taste of this\ncake, you'll never forget its sweetness.",
   "Required Ingredient 1": "Tabantha Wheat",
   "Required Ingredient 2": "Cane Sugar",
   "Required Ingredient 3": "Monster Extract",
   "Required Ingredient 4": "Goat Butter",
   "Required Ingredient 5": "-",
   "Cooking Method": "Cooking Pot"
 },
 {
   "Recipe #": 140,
   "Name": "Dark Stew",
   "Inventory Icon": "https://raw.githubusercontent.com/TOTKSheet/TOTKImages/main/Items/Item_Cook_S_05.png",
   "Caption": "A daring dish of dark clump stewed with\nmeat and fish. What a surprise!",
   "Required Ingredient 1": "Dark Clump",
   "Required Ingredient 2": "Meat",
   "Required Ingredient 3": "Fish",
   "Required Ingredient 4": "-",
   "Required Ingredient 5": "-",
   "Cooking Method": "Cooking Pot"
 },
 {
   "Recipe #": 141,
   "Name": "Dark Soup",
   "Inventory Icon": "https://raw.githubusercontent.com/TOTKSheet/TOTKImages/main/Items/Item_Cook_S_07.png",
   "Caption": "A gooey soup built on stewed dark clump.\nOne could get lost in its swirls and flavors.",
   "Required Ingredient 1": "Dark Clump",
   "Required Ingredient 2": "Tabantha Wheat",
   "Required Ingredient 3": "Goat Butter",
   "Required Ingredient 4": "Fresh Milk",
   "Required Ingredient 5": "-",
   "Cooking Method": "Cooking Pot"
 },
 {
   "Recipe #": 142,
   "Name": "Dark Curry",
   "Inventory Icon": "https://raw.githubusercontent.com/TOTKSheet/TOTKImages/main/Items/Item_Cook_S_08.png",
   "Caption": "A hard-hitting curry with a dark-clump\nbase, whose flavor is hard to hide.",
   "Required Ingredient 1": "Dark Clump",
   "Required Ingredient 2": "Goron Spice",
   "Required Ingredient 3": "Hylian Rice",
   "Required Ingredient 4": "-",
   "Required Ingredient 5": "-",
   "Cooking Method": "Cooking Pot"
 },
 {
   "Recipe #": 143,
   "Name": "Dark Rice Ball",
   "Inventory Icon": "https://raw.githubusercontent.com/TOTKSheet/TOTKImages/main/Items/Item_Cook_S_06.png",
   "Caption": "A bold rice ball made with dark clump and\nHylian rice. Its flavor is unforgettable!",
   "Required Ingredient 1": "Dark Clump",
   "Required Ingredient 2": "Rock Salt",
   "Required Ingredient 3": "Hylian Rice",
   "Required Ingredient 4": "-",
   "Required Ingredient 5": "-",
   "Cooking Method": "Cooking Pot"
 },
 {
   "Recipe #": 144,
   "Name": "Dark Cake",
   "Inventory Icon": "https://raw.githubusercontent.com/TOTKSheet/TOTKImages/main/Items/Item_Cook_S_09.png",
   "Caption": "An unusual dark-clump cake with a unique\nflavor that may be impossible to fully describe.",
   "Required Ingredient 1": "Dark Clump",
   "Required Ingredient 2": "Cane Sugar",
   "Required Ingredient 3": "Tabantha Wheat",
   "Required Ingredient 4": "Goat Butter",
   "Required Ingredient 5": "-",
   "Cooking Method": "Cooking Pot"
 },
 {
   "Recipe #": 145,
   "Name": "Dubious Food",
   "Inventory Icon": "https://raw.githubusercontent.com/TOTKSheet/TOTKImages/main/Items/Item_Cook_O_01.png",
   "Caption": "It's too gross to even look at. A bizarre smell\nissues forth from this heap. Eating it won't\nhurt you though...probably.",
   "Required Ingredient 1": "Invalid Recipe",
   "Required Ingredient 2": "-",
   "Required Ingredient 3": "-",
   "Required Ingredient 4": "-",
   "Required Ingredient 5": "-",
   "Cooking Method": "Cooking Pot"
 },
 {
   "Recipe #": 146,
   "Name": "Rock-Hard Food",
   "Inventory Icon": "https://raw.githubusercontent.com/TOTKSheet/TOTKImages/main/Items/Item_Cook_O_02.png",
   "Caption": "A dish gone awry after adding the wrong\ningredient. Chewing your way through this\nwon't be fun, but it will fill you up when\nyou're between a rock and a hard place.",
   "Required Ingredient 1": "Ore",
   "Required Ingredient 2": "-",
   "Required Ingredient 3": "-",
   "Required Ingredient 4": "-",
   "Required Ingredient 5": "-",
   "Cooking Method": "Cooking Pot"
 },
 {
   "Recipe #": 215,
   "Name": "Energizing Elixir",
   "Inventory Icon": "https://raw.githubusercontent.com/TOTKSheet/TOTKImages/main/Items/Item_Cook_C_17_StaminaRecover.png",
   "Caption": "Restores your stamina, which is used when\nperforming physical actions such as \nclimbing walls or swimming.",
   "Required Ingredient 1": "Enemy",
   "Required Ingredient 2": "Energetic Rhino Beetle / Restless Cricket",
   "Required Ingredient 3": "-",
   "Required Ingredient 4": "-",
   "Required Ingredient 5": "-",
   "Cooking Method": "Cooking Pot"
 },
 {
   "Recipe #": 216,
   "Name": "Hasty Elixir",
   "Inventory Icon": "https://raw.githubusercontent.com/TOTKSheet/TOTKImages/main/Items/Item_Cook_C_17_AllSpeed.png",
   "Caption": "Grants a low-level haste effect, which\nboosts your movement speed while\nrunning, swimming, or climbing.",
   "Required Ingredient 1": "Enemy",
   "Required Ingredient 2": "Hot-Footed Frog / Hightail Lizard",
   "Required Ingredient 3": "-",
   "Required Ingredient 4": "-",
   "Required Ingredient 5": "-",
   "Cooking Method": "Cooking Pot"
 },
 {
   "Recipe #": 217,
   "Name": "Spicy Elixir",
   "Inventory Icon": "https://raw.githubusercontent.com/TOTKSheet/TOTKImages/main/Items/Item_Cook_C_17_ResistCold.png",
   "Caption": "Grants a low-level warming effect, increasing\nyour resistance to cold environments. Very\nuseful when exploring snow-covered\nmountains.",
   "Required Ingredient 1": "Enemy",
   "Required Ingredient 2": "Summerwing Butterfly / Warm Darner",
   "Required Ingredient 3": "-",
   "Required Ingredient 4": "-",
   "Required Ingredient 5": "-",
   "Cooking Method": "Cooking Pot"
 },
 {
   "Recipe #": 218,
   "Name": "Chilly Elixir",
   "Inventory Icon": "https://raw.githubusercontent.com/TOTKSheet/TOTKImages/main/Items/Item_Cook_C_17_ResistHot.png",
   "Caption": "Grants a low-level cooling effect, raising\nyour body's resistance to heat. Crucial for\nlong journeys through the desert.",
   "Required Ingredient 1": "Enemy",
   "Required Ingredient 2": "Winterwing Butterfly / Cold Darner",
   "Required Ingredient 3": "-",
   "Required Ingredient 4": "-",
   "Required Ingredient 5": "-",
   "Cooking Method": "Cooking Pot"
 },
 {
   "Recipe #": 219,
   "Name": "Electro Elixir",
   "Inventory Icon": "https://raw.githubusercontent.com/TOTKSheet/TOTKImages/main/Items/Item_Cook_C_17_ResistElectric.png",
   "Caption": "Grants a low-level resistance to electricity.\nUseful against enemies with electrical\nattacks.",
   "Required Ingredient 1": "Enemy",
   "Required Ingredient 2": "Thunderwing Butterfly / Electric Darner",
   "Required Ingredient 3": "-",
   "Required Ingredient 4": "-",
   "Required Ingredient 5": "-",
   "Cooking Method": "Cooking Pot"
 },
 {
   "Recipe #": 220,
   "Name": "Fireproof Elixir",
   "Inventory Icon": "https://raw.githubusercontent.com/TOTKSheet/TOTKImages/main/Items/Item_Cook_C_17_ResistBurn.png",
   "Caption": "Grants a fireproof effect, which prevents your\nbody from catching fire.\nBe sure to pack this when venturing out\nto explore caves in Death Mountain.",
   "Required Ingredient 1": "Enemy",
   "Required Ingredient 2": "Smotherwing Butterfly / Fireproof Lizard",
   "Required Ingredient 3": "-",
   "Required Ingredient 4": "-",
   "Required Ingredient 5": "-",
   "Cooking Method": "Cooking Pot"
 },
 {
   "Recipe #": 221,
   "Name": "Mighty Elixir",
   "Inventory Icon": "https://raw.githubusercontent.com/TOTKSheet/TOTKImages/main/Items/Item_Cook_C_17_AttackUp.png",
   "Caption": "Grants a low-level might effect, which\nstrengthens your body and mind to boost\nyour attack power with all weapons.",
   "Required Ingredient 1": "Enemy",
   "Required Ingredient 2": "Bladed Rhino Beetle",
   "Required Ingredient 3": "-",
   "Required Ingredient 4": "-",
   "Required Ingredient 5": "-",
   "Cooking Method": "Cooking Pot"
 },
 {
   "Recipe #": 222,
   "Name": "Tough Elixir",
   "Inventory Icon": "https://raw.githubusercontent.com/TOTKSheet/TOTKImages/main/Items/Item_Cook_C_17_DefenseUp.png",
   "Caption": "Grants a low-level toughness effect, which\nfortifies your bones to strengthen your\ndefense. Best to use before facing off\nagainst hard-hitting enemies.",
   "Required Ingredient 1": "Enemy",
   "Required Ingredient 2": "Rugged Rhino Beetle",
   "Required Ingredient 3": "-",
   "Required Ingredient 4": "-",
   "Required Ingredient 5": "-",
   "Cooking Method": "Cooking Pot"
 },
 {
   "Recipe #": 223,
   "Name": "Sneaky Elixir",
   "Inventory Icon": "https://raw.githubusercontent.com/TOTKSheet/TOTKImages/main/Items/Item_Cook_C_17_QuietnessUp.png",
   "Caption": "Grants a low-level stealth effect, which\ncalms the nerves and silences footfalls.\nAllows you to move about undetected by\nmonsters and animals.",
   "Required Ingredient 1": "Enemy",
   "Required Ingredient 2": "Sunset Firefly",
   "Required Ingredient 3": "-",
   "Required Ingredient 4": "-",
   "Required Ingredient 5": "-",
   "Cooking Method": "Cooking Pot"
 },
 {
   "Recipe #": 224,
   "Name": "Sticky Elixir",
   "Inventory Icon": "https://raw.githubusercontent.com/TOTKSheet/TOTKImages/main/Items/Item_Cook_C_17_NotSlippy.png",
   "Caption": "Grants a low-level slip resistance to keep you\nfrom slipping on wet surfaces. Its highly\nabsorptive ingredients make it a must-have\nfor sudden rainfalls.",
   "Required Ingredient 1": "Enemy",
   "Required Ingredient 2": "Sticky Frog / Sticky Lizard",
   "Required Ingredient 3": "-",
   "Required Ingredient 4": "-",
   "Required Ingredient 5": "-",
   "Cooking Method": "Cooking Pot"
 },
 {
   "Recipe #": 225,
   "Name": "Bright Elixir",
   "Inventory Icon": "https://raw.githubusercontent.com/TOTKSheet/TOTKImages/main/Items/Item_Cook_C_17_LightEmission.png",
   "Caption": "Grants a low-level glow effect, illuminating\nyour immediate surroundings. This faint\nluminescence is a boon in dark places.",
   "Required Ingredient 1": "Enemy",
   "Required Ingredient 2": "Deep Firefly",
   "Required Ingredient 3": "-",
   "Required Ingredient 4": "-",
   "Required Ingredient 5": "-",
   "Cooking Method": "Cooking Pot"
 },
 {
   "Recipe #": 226,
   "Name": "Enduring Elixir",
   "Inventory Icon": "https://raw.githubusercontent.com/TOTKSheet/TOTKImages/main/Items/Item_Cook_C_17_ExStaminaMaxUp.png",
   "Caption": "Restores stamina and temporarily extends\nyour Stamina Wheel. The additional stamina\nwill disappear as it's used.",
   "Required Ingredient 1": "Enemy",
   "Required Ingredient 2": "Tireless Frog",
   "Required Ingredient 3": "-",
   "Required Ingredient 4": "-",
   "Required Ingredient 5": "-",
   "Cooking Method": "Cooking Pot"
 },
 {
   "Recipe #": 227,
   "Name": "Hearty Elixir",
   "Inventory Icon": "https://raw.githubusercontent.com/TOTKSheet/TOTKImages/main/Items/Item_Cook_C_17_LifeMaxUp.png",
   "Caption": "Restores you to full health and increases\nyour maximum hearts. The additional hearts\nare lost as you take damage.",
   "Required Ingredient 1": "Enemy",
   "Required Ingredient 2": "Hearty Lizard",
   "Required Ingredient 3": "-",
   "Required Ingredient 4": "-",
   "Required Ingredient 5": "-",
   "Cooking Method": "Cooking Pot"
 },
 {
   "Recipe #": 228,
   "Name": "Fairy Tonic",
   "Inventory Icon": "https://raw.githubusercontent.com/TOTKSheet/TOTKImages/main/Items/Item_Cook_C_16.png",
   "Caption": "This powerful recovery elixir harnesses the\npower of fairies. It has a sweet fragrance.",
   "Required Ingredient 1": "Fairy",
   "Required Ingredient 2": "-",
   "Required Ingredient 3": "-",
   "Required Ingredient 4": "-",
   "Required Ingredient 5": "-",
   "Cooking Method": "Cooking Pot"
 }
]